archivesspace_jsonmodel_converter/__init__.py
archivesspace_jsonmodel_converter/configurator.py
archivesspace_jsonmodel_converter/crosswalk_reader.py
archivesspace_jsonmodel_converter/logger.py
archivesspace_jsonmodel_converter/main.py
archivesspace_jsonmodel_converter/subjects.py
archivesspace_jsonmodel_converter-0.0.1.dist-info/METADATA
archivesspace_jsonmodel_converter-0.0.1.dist-info/WHEEL
archivesspace_jsonmodel_converter-0.0.1.dist-info/entry_points.txt
archivesspace_jsonmodel_converter-0.0.1.dist-info/top_level.txt
archivesspace_jsonmodel_converter-0.0.1.dist-info/RECORD
