Metadata-Version: 2.1
Name: archivesspace-jsonmodel-converter
Version: 0.0.1
Summary: A tool for converting data into ArchivesSpace JSONModel objects.
Home-page: https://github.com/pobocks/archivesspace_jsonmodel_converter
Author: Dave and Bobbi Fox
Author-email: pobocks@gmail.com
Classifier: Programming Language :: Python :: 3
Classifier: License :: OSI Approved :: MIT License
Classifier: Operating System :: OS Independent
Requires-Python: >=3.7
Requires-Dist: attrs (<23,>=22.2.0)
Requires-Dist: boltons (<22,>=21.0.0)
Requires-Dist: click (<9,>=8.1.3)
Requires-Dist: structlog (<22,>=21.1.0)
Requires-Dist: python-json-logger (<3pytest>=7.0.1,<8,>=2.0.2)
Requires-Dist: python-dotenv (<=0.19.1,>0.19.0)
Requires-Dist: requests (<3,>=2.27.1)
Requires-Dist: psycopg (<4,>=3.1.4)
Requires-Dist: typing-extensions (==4.4.0)
Requires-Dist: archivessnake (>=0.9.1)
